maddg/_residuals.py
maddg/_sim_launcher.py
maddg-0.1.4.dist-info/licenses/LICENSE.txt
madlib/__init__.py
madlib/_maneuver.py
madlib/_observation.py
madlib/_satellite.py
madlib/_sensor.py
madlib/_sensor_collection.py
madlib/_utils.py
maddg-0.1.4.dist-info/METADATA
maddg-0.1.4.dist-info/WHEEL
maddg-0.1.4.dist-info/top_level.txt
maddg-0.1.4.dist-info/RECORD
