Metadata-Version: 2.4
Name: MaDDG
Version: 0.1.4
Summary: Maneuver Detection Data Generation
Home-page: https://github.com/mit-ll/MaDDG
Author: see AUTHORS.md
Author-email: michael.kotson@ll.mit.edu
License: MIT
Project-URL: Documentation, https://maddg.readthedocs.io/en/latest/
Platform: any
Classifier: Development Status :: 4 - Beta
Classifier: Programming Language :: Python
Requires-Python: <3.13,>=3.11
License-File: LICENSE.txt
Requires-Dist: AstroForge
Requires-Dist: requests>=2.18.4
Requires-Dist: astropy>=5.3.1
Requires-Dist: matplotlib>=3.7.2
Requires-Dist: numpy==1.26.4
Requires-Dist: pandas>=2.0.3
Requires-Dist: hydra-core>=1.3.2
Requires-Dist: hydra-submitit-launcher>=1.2.0
Requires-Dist: hydra-zen>=0.11.0
Requires-Dist: submitit>=1.4.5
Requires-Dist: pyyaml>=6.0.1
Requires-Dist: jsonschema>=4.19.0
Provides-Extra: testing
Requires-Dist: setuptools; extra == "testing"
Requires-Dist: pytest; extra == "testing"
Requires-Dist: pytest-cov; extra == "testing"
Dynamic: license-file
